stacklet/client/__init__.py
stacklet/client/platform/__init__.py
stacklet/client/platform/cli.py
stacklet/client/platform/client.py
stacklet/client/platform/cognito.py
stacklet/client/platform/config.py
stacklet/client/platform/context.py
stacklet/client/platform/exceptions.py
stacklet/client/platform/executor.py
stacklet/client/platform/formatter.py
stacklet/client/platform/graphql.py
stacklet/client/platform/registry.py
stacklet/client/platform/utils.py
stacklet/client/platform/commands/__init__.py
stacklet/client/platform/commands/account.py
stacklet/client/platform/commands/accountgroup.py
stacklet/client/platform/commands/binding.py
stacklet/client/platform/commands/cube.py
stacklet/client/platform/commands/graphql.py
stacklet/client/platform/commands/policy.py
stacklet/client/platform/commands/policycollection.py
stacklet/client/platform/commands/repository.py
stacklet/client/platform/commands/user.py
stacklet/client/platform/vendored/__init__.py
stacklet/client/platform/vendored/auth.py
stacklet/client/platform/vendored/auth_landing_pages/__init__.py
stacklet/client/platform/vendored/auth_landing_pages/fail.html
stacklet/client/platform/vendored/auth_landing_pages/ok.html
stacklet_client_platform-2026.1.0.dist-info/METADATA
stacklet_client_platform-2026.1.0.dist-info/WHEEL
stacklet_client_platform-2026.1.0.dist-info/entry_points.txt
stacklet_client_platform-2026.1.0.dist-info/licenses/LICENSE
stacklet_client_platform-2026.1.0.dist-info/RECORD
