Metadata-Version: 2.4
Name: stacklet.client.platform
Version: 2026.1.0
Summary: Stacklet Platform Client
Author-email: Stacklet Engineering <foss+stacklet-admin@stacklet.io>
Maintainer-email: Stacklet Engineering <foss+stacklet-admin@stacklet.io>
License-Expression: Apache-2.0
License-File: LICENSE
Requires-Python: <=3.14,>=3.9
Requires-Dist: boto3<2,>=1.39.16
Requires-Dist: charset-normalizer<4,>=3.4.2
Requires-Dist: click<9,>=8.0.1
Requires-Dist: jmespath<2,>=1.0.1
Requires-Dist: jsonschema<5,>=4.9.0
Requires-Dist: pyjwt<3,>=2.4.0
Requires-Dist: pyyaml~=6.0
Requires-Dist: requests<3,>=2.32.4
